ceda_directory_tree/__init__.py
ceda_directory_tree/dataset_node.py
ceda_directory_tree/directory_node.py
ceda_directory_tree/examples/__init__.py
ceda_directory_tree/examples/speed_test.py
ceda_directory_tree-1.2.0.dist-info/LICENSE
ceda_directory_tree-1.2.0.dist-info/METADATA
ceda_directory_tree-1.2.0.dist-info/WHEEL
ceda_directory_tree-1.2.0.dist-info/entry_points.txt
ceda_directory_tree-1.2.0.dist-info/RECORD
