Metadata-Version: 2.3
Name: ceda-directory-tree
Version: 1.2.0
Summary: Python package to create a virtual tree data structure to represent a directory tree to be used for efficient search
License: BSD 3
Author: Daniel Westwood
Author-email: daniel.westwood@stfc.ac.uk
Requires-Python: >=3.9,<4
Classifier: Development Status :: 3 - Alpha
Classifier: Environment :: Plugins
Classifier: Intended Audience :: Developers
Classifier: License :: OSI Approved :: BSD License
Classifier: Natural Language :: English
Classifier: Programming Language :: Python :: 3
Requires-Dist: anytree (>=2.12.1,<3.0.0)
Requires-Dist: requests (>=2.32.3,<3.0.0)
Requires-Dist: tox (>=4.24.1,<5.0.0)
Project-URL: Repository, https://github.com/cedadev/ceda-directory-tree
